polofutures/__init__.py
polofutures/rest/__init__.py
polofutures/rest/client.py
polofutures/rest/core.py
polofutures/rest/market.py
polofutures/rest/trade.py
polofutures/rest/user.py
polofutures/ws/__init__.py
polofutures/ws/client.py
polo_futures_sdk-0.1.dist-info/LICENSE
polo_futures_sdk-0.1.dist-info/METADATA
polo_futures_sdk-0.1.dist-info/WHEEL
polo_futures_sdk-0.1.dist-info/top_level.txt
polo_futures_sdk-0.1.dist-info/RECORD
